leapy/__init__.py
leapy/dask/__init__.py
leapy/dask/pipeline/FeaturePipeline.py
leapy/dask/pipeline/__init__.py
leapy/dask/pipeline/test/__init__.py
leapy/dask/pipeline/test/test_FeaturePipeline.py
leapy/dask/transformers/OneHotEncoder.py
leapy/dask/transformers/__init__.py
leapy/dask/transformers/export/OneHotEncoderExporter.py
leapy/dask/transformers/export/TrivialExporter.py
leapy/dask/transformers/export/__init__.py
leapy/dask/transformers/export/test/__init__.py
leapy/dask/transformers/export/test/test_OneHotEncoderExporter.py
leapy/dask/transformers/export/test/test_TrivialExporter.py
leapy/dask/transformers/test/__init__.py
leapy/dask/transformers/test/test_OneHotEncoder.py
leapy/runtime/__init__.py
leapy/runtime/pipeline/FeaturePipelineRuntime.py
leapy/runtime/pipeline/__init__.py
leapy/runtime/pipeline/test/__init__.py
leapy/runtime/pipeline/test/test_FeaturePipelineRuntime.py
leapy/runtime/transformers/OneHotEncoderRuntime.py
leapy/runtime/transformers/SelectorRuntime.py
leapy/runtime/transformers/__init__.py
leapy/runtime/transformers/test/__init__.py
leapy/runtime/transformers/test/test_OneHotEncoderRuntime.py
leapy/runtime/transformers/test/test_SelectorRuntime.py
leapy/serve/__init__.py
leapy/serve/leap.py
leapy-0.1.0.dist-info/LICENSE.txt
leapy-0.1.0.dist-info/METADATA
leapy-0.1.0.dist-info/WHEEL
leapy-0.1.0.dist-info/entry_points.txt
leapy-0.1.0.dist-info/top_level.txt
leapy-0.1.0.dist-info/RECORD
