Metadata-Version: 2.1
Name: leapy
Version: 0.1.0
Summary: Real-time inference pipelines
Home-page: http://github.com/nonabelian/leapy
Author: Dylan Albrecht
Author-email: djalbrecht@email.wm.edu
License: new BSD
Platform: UNKNOWN
Classifier: Intended Audience :: Science/Research
Classifier: Intended Audience :: Developers
Classifier: License :: OSI Approved
Classifier: Programming Language :: Python
Classifier: Topic :: Software Development
Classifier: Topic :: Scientific/Engineering
Classifier: Operating System :: Microsoft :: Windows
Classifier: Operating System :: POSIX
Classifier: Operating System :: Unix
Classifier: Operating System :: MacOS
Classifier: Programming Language :: Python :: 3.7
Requires-Dist: pandas (>=0.24.2)
Requires-Dist: dask (>=1.1.4)
Requires-Dist: dask-ml (>=0.12.0)
Requires-Dist: numpy (>=1.16.2)
Requires-Dist: scikit-learn (>=0.20.3)
Requires-Dist: marshmallow (>=2.19.2)
Requires-Dist: docker (==3.7.2)
